anikoto/__init__.py
anikoto/anikoto.py
anikoto-3.0.0.dist-info/METADATA
anikoto-3.0.0.dist-info/WHEEL
anikoto-3.0.0.dist-info/entry_points.txt
anikoto-3.0.0.dist-info/top_level.txt
anikoto-3.0.0.dist-info/RECORD
