Metadata-Version: 2.4
Name: anikoto
Version: 3.0.0
Summary: Download Anime from https://anikoto.tv/
Home-page: https://github.com/testingbetaversion/anikoto
Author: testingbetaversion
Author-email: testingbetaversion <moonmuaaz@gmail.com>
License: MIT
Project-URL: Homepage, https://github.com/testingbetaversion/anikoto
Project-URL: Source, https://github.com/testingbetaversion/anikoto
Classifier: Programming Language :: Python :: 3
Classifier: License :: OSI Approved :: MIT License
Classifier: Operating System :: OS Independent
Requires-Python: >=3.6
Requires-Dist: requests
Requires-Dist: yt-dlp
Requires-Dist: bs4
Dynamic: author
Dynamic: home-page
Dynamic: requires-python
